smalk_disk_check/__init__.py
smalk_disk_check/args_parsing.py
smalk_disk_check/disk.py
smalk_disk_check/install_checking.py
smalk_disk_check/key_manager.py
smalk_disk_check/main.py
smalk_disk_check/mdadm_handler.py
smalk_disk_check/process.py
smalk_disk_check/setting_manager.py
smalk_disk_check/smart_handler.py
smalk_disk_check/temp_handler.py
smalk_disk_check-0.2.1.dist-info/licenses/LICENSE
smalk_disk_check-0.2.1.dist-info/METADATA
smalk_disk_check-0.2.1.dist-info/WHEEL
smalk_disk_check-0.2.1.dist-info/entry_points.txt
smalk_disk_check-0.2.1.dist-info/top_level.txt
smalk_disk_check-0.2.1.dist-info/RECORD
