Metadata-Version: 2.4
Name: smalk_disk_check
Version: 0.2.1
Summary: smalk implementation for disk checking and monitoring.
Author-email: The220th <The220th@gmail.com>
License-Expression: MIT
Project-URL: Homepage, https://github.com/The220th/smalk_disk_check
Project-URL: Issues, https://github.com/The220th/smalk_disk_check/issues
Classifier: Programming Language :: Python :: 3
Classifier: Operating System :: POSIX :: Linux
Requires-Python: >=3.7
License-File: LICENSE
Requires-Dist: alerk_pack
Requires-Dist: ksupk
Requires-Dist: pySMART
Requires-Dist: requests
Requires-Dist: pyyaml
Requires-Dist: argparse
Dynamic: license-file
